biobb_md/__init__.py
biobb_md/gromacs/__init__.py
biobb_md/gromacs/common.py
biobb_md/gromacs/editconf.py
biobb_md/gromacs/genion.py
biobb_md/gromacs/genrestr.py
biobb_md/gromacs/gmxselect.py
biobb_md/gromacs/grompp.py
biobb_md/gromacs/grompp_mdrun.py
biobb_md/gromacs/make_ndx.py
biobb_md/gromacs/mdrun.py
biobb_md/gromacs/pdb2gmx.py
biobb_md/gromacs/solvate.py
biobb_md/gromacs_extra/__init__.py
biobb_md/gromacs_extra/append_ligand.py
biobb_md/gromacs_extra/ndx2resttop.py
biobb_md/test/__init__.py
biobb_md-3.7.2.dist-info/LICENSE
biobb_md-3.7.2.dist-info/METADATA
biobb_md-3.7.2.dist-info/WHEEL
biobb_md-3.7.2.dist-info/entry_points.txt
biobb_md-3.7.2.dist-info/top_level.txt
biobb_md-3.7.2.dist-info/RECORD
