Metadata-Version: 2.1
Name: biobb-md
Version: 3.7.2
Summary: Deprecated Package: biobb_md is no longer maintained and has been superseded by the biobb_gromacs package. Biobb_md is the Biobb module collection to perform molecular dynamics simulations.
Home-page: https://github.com/bioexcel/biobb_md
Author: Biobb developers
Author-email: pau.andrio@bsc.es
License: UNKNOWN
Project-URL: Documentation, http://biobb_md.readthedocs.io/en/latest/
Project-URL: Bioexcel, https://bioexcel.eu/
Keywords: Bioinformatics Workflows BioExcel Compatibility
Platform: UNKNOWN
Classifier: Development Status :: 3 - Alpha
Classifier: Programming Language :: Python :: 3.7
Classifier: License :: OSI Approved :: Apache Software License
Classifier: Operating System :: MacOS :: MacOS X
Classifier: Operating System :: POSIX
Requires-Python: ==3.7.*
Requires-Dist: biobb-common (==3.7.0)
